bfi/__init__.py
bfi/__main__.py
bfi/examples/LostKingdom.b
bfi/examples/TheBrainfuckedLoneWolf.b
bfi/examples/bfcl.bf
bfi/examples/bitwidth.bf
bfi/examples/collatz.b
bfi/examples/eoftest.b
bfi/examples/fib.b
bfi/examples/gameoflife.b
bfi/examples/hanoi.b
bfi/examples/hello_world.b
bfi/examples/mandel.b
bfi/examples/numwarp.b
bfi/examples/primes.bf
bfi/examples/rot13.b
bfi/examples/sierpinski.b
bfi/test/samples/bitwidth.bf
bfi/test/samples/collatz.b
bfi/test/samples/eoftest.b
bfi/test/samples/hello_world.b
bfi/test/samples/numwarp.b
bfi/test/samples/rot13.b
bfi-1.1.1.dist-info/LICENSE
bfi-1.1.1.dist-info/METADATA
bfi-1.1.1.dist-info/WHEEL
bfi-1.1.1.dist-info/entry_points.txt
bfi-1.1.1.dist-info/top_level.txt
bfi-1.1.1.dist-info/RECORD
