Metadata-Version: 2.1
Name: bfi
Version: 1.1.1
Summary: A fast optimizing Brainfuck interpreter in pure python
Home-page: http://github.com/eriknyquist/bfi
Author: Erik Nyquist
Author-email: eknyquist@gmail.com
License: MIT
Platform: UNKNOWN
Classifier: License :: OSI Approved :: MIT License
Classifier: Operating System :: OS Independent
Classifier: Programming Language :: Python
Classifier: Natural Language :: English
Classifier: Intended Audience :: Developers
Classifier: Intended Audience :: Science/Research
Classifier: Intended Audience :: Education
Classifier: Intended Audience :: Information Technology
Classifier: Programming Language :: Python :: 2
Classifier: Programming Language :: Python :: 2.7
Classifier: Programming Language :: Python :: 3
Classifier: Programming Language :: Python :: 3.11
